cai_causal_graph/__init__.py
cai_causal_graph/causal_graph.py
cai_causal_graph/exceptions.py
cai_causal_graph/graph_components.py
cai_causal_graph/identify_utils.py
cai_causal_graph/interfaces.py
cai_causal_graph/metadata_handler.py
cai_causal_graph/time_series_causal_graph.py
cai_causal_graph/type_definitions.py
cai_causal_graph/utils.py
cai_causal_graph-0.5.14.dist-info/LICENSE
cai_causal_graph-0.5.14.dist-info/METADATA
cai_causal_graph-0.5.14.dist-info/WHEEL
cai_causal_graph-0.5.14.dist-info/RECORD
