Metadata-Version: 2.1
Name: cai-causal-graph
Version: 0.5.14
Summary: A Causal AI package for causal graphs.
Home-page: https://causalgraph.causalens.com/
License: Apache-2.0
Author: causaLens
Author-email: opensource@causalens.com
Requires-Python: >=3.10.0,<3.15.0
Classifier: License :: OSI Approved :: Apache Software License
Classifier: Programming Language :: Python :: 3
Classifier: Programming Language :: Python :: 3.10
Classifier: Programming Language :: Python :: 3.11
Classifier: Programming Language :: Python :: 3.12
Requires-Dist: mypy-extensions (>=1.0.0,<2.0.0)
Requires-Dist: networkx (>=3.0.0,<3.3.0)
Requires-Dist: numpy (>=1.18.0,<3.0.0)
Requires-Dist: pandas (>=1.0.0,<3.0.0)
Project-URL: Documentation, https://causalgraph.causalens.com/
Project-URL: Repository, https://github.com/causalens/cai-causal-graph
